incognia/__init__.py
incognia/api.py
incognia/base_request.py
incognia/datetime_util.py
incognia/endpoints.py
incognia/exceptions.py
incognia/feedback_events.py
incognia/json_util.py
incognia/models.py
incognia/singleton.py
incognia/token_manager.py
incognia_python-3.4.0.dist-info/licenses/LICENSE.txt
incognia_python-3.4.0.dist-info/METADATA
incognia_python-3.4.0.dist-info/WHEEL
incognia_python-3.4.0.dist-info/top_level.txt
incognia_python-3.4.0.dist-info/RECORD
