Metadata-Version: 2.4
Name: incognia-python
Version: 3.4.0
Summary: Python lightweight client library for Incognia APIs
Home-page: https://github.com/inloco/incognia-python
Author: Incognia
Author-email: opensource@incognia.com
License: MIT
Classifier: Operating System :: OS Independent
Classifier: License :: OSI Approved :: MIT License
Classifier: Programming Language :: Python :: 3.8
Classifier: Programming Language :: Python :: 3.9
License-File: LICENSE.txt
Requires-Dist: requests
Dynamic: license-file
